datastructures/__init__.py
datastructures/graphs.py
datastructures/heap.py
datastructures/linear.py
datastructures/my_functions.py
datastructures/sorts.py
datastructures/strings.py
datastructures/trees/__init__.py
datastructures/trees/nodes.py
datastructures/trees/trees.py
slav_eeik_datastructures-1.1.dist-info/LICENSE
slav_eeik_datastructures-1.1.dist-info/METADATA
slav_eeik_datastructures-1.1.dist-info/WHEEL
slav_eeik_datastructures-1.1.dist-info/top_level.txt
slav_eeik_datastructures-1.1.dist-info/RECORD
