Metadata-Version: 2.1
Name: slav-eeik-datastructures
Version: 1.1
Summary: Simple datastructures library with documentation.
Home-page: https://github.com/zhukovrost/datastructures
Author: Zhukov Rostislav
Author-email: 2rosf.zhukov@gmail.com
License: MIT
Project-URL: Source Code, https://github.com/zhukovrost/datastructures
Project-URL: Documentation, https://zhukovrost.github.io/datastructures/
Classifier: Development Status :: 3 - Alpha
Classifier: Environment :: Console
Classifier: Intended Audience :: Developers
Classifier: Intended Audience :: Science/Research
Classifier: License :: OSI Approved :: MIT License
Classifier: Programming Language :: Python :: 3.10
Requires-Python: >=3.10
License-File: LICENSE
Provides-Extra: dev
Requires-Dist: sphinx; extra == "dev"
Requires-Dist: sphinx-rtd-theme; extra == "dev"
Requires-Dist: pytest; extra == "dev"
